{
    "X3": [
        {
            "Id": 5,
            "Year": 2017,
            "TypeDesc": "Sport Utility Vehicle",
            "MfgDesc": "BMW",
            "MakeTrim": "X3",
            "DriveTypeDesc": "Not Available",
            "Engine": "All",
            "Trans": null,
            "Notes": null,
            "TowDesc": "Bumper Pull - Weight Carrying",
            "GearRatio": null,
            "TowCapacity": 3500
        }
    ],
    "X4": [
        {
            "Id": 6,
            "Year": 2017,
            "TypeDesc": "Sport Utility Vehicle",
            "MfgDesc": "BMW",
            "MakeTrim": "X4",
            "DriveTypeDesc": "Not Available",
            "Engine": "All",
            "Trans": null,
            "Notes": null,
            "TowDesc": "Bumper Pull - Weight Carrying",
            "GearRatio": null,
            "TowCapacity": 3500
        }
    ],
    "X5": [
        {
            "Id": 7,
            "Year": 2017,
            "TypeDesc": "Sport Utility Vehicle",
            "MfgDesc": "BMW",
            "MakeTrim": "X5",
            "DriveTypeDesc": "Not Available",
            "Engine": "All",
            "Trans": null,
            "Notes": null,
            "TowDesc": "Bumper Pull - Weight Carrying",
            "GearRatio": null,
            "TowCapacity": 6000
        }
    ],
    "X6": [
        {
            "Id": 8,
            "Year": 2017,
            "TypeDesc": "Sport Utility Vehicle",
            "MfgDesc": "BMW",
            "MakeTrim": "X6",
            "DriveTypeDesc": "Not Available",
            "Engine": "All",
            "Trans": null,
            "Notes": null,
            "TowDesc": "Bumper Pull - Weight Carrying",
            "GearRatio": null,
            "TowCapacity": 6000
        }
    ]
}