[
    {
        "Year": 2006,
        "Make": "Mercedes-Benz",
        "ModelTrim": "G 320",
        "TowingCapacity": {
            "Id": 15973,
            "Year": 2006,
            "TypeDesc": "Sport Utility Vehicle",
            "MfgDesc": "Mercedes-Benz",
            "MakeTrim": "G 320",
            "DriveTypeDesc": "Not Available",
            "Engine": "V-6",
            "Trans": null,
            "Notes": null,
            "TowDesc": "Bumper Pull - Weight Carrying",
            "GearRatio": null,
            "TowCapacity": 7840
        }
    },
    {
        "Year": 2006,
        "Make": "Mercedes-Benz",
        "ModelTrim": "G 500",
        "TowingCapacity": {
            "Id": 15974,
            "Year": 2006,
            "TypeDesc": "Sport Utility Vehicle",
            "MfgDesc": "Mercedes-Benz",
            "MakeTrim": "G 500",
            "DriveTypeDesc": "Not Available",
            "Engine": "V-8",
            "Trans": null,
            "Notes": null,
            "TowDesc": "Bumper Pull - Weight Carrying",
            "GearRatio": null,
            "TowCapacity": 7840
        }
    },
    {
        "Year": 2006,
        "Make": "Mercedes-Benz",
        "ModelTrim": "G 55 AMG",
        "TowingCapacity": {
            "Id": 15975,
            "Year": 2006,
            "TypeDesc": "Sport Utility Vehicle",
            "MfgDesc": "Mercedes-Benz",
            "MakeTrim": "G 55 AMG",
            "DriveTypeDesc": "Not Available",
            "Engine": "V-8",
            "Trans": null,
            "Notes": null,
            "TowDesc": "Bumper Pull - Weight Carrying",
            "GearRatio": null,
            "TowCapacity": 7842
        }
    },
    {
        "Year": 2006,
        "Make": "Mercedes-Benz",
        "ModelTrim": "ML 350",
        "TowingCapacity": {
            "Id": 15976,
            "Year": 2006,
            "TypeDesc": "Sport Utility Vehicle",
            "MfgDesc": "Mercedes-Benz",
            "MakeTrim": "ML 350",
            "DriveTypeDesc": "Not Available",
            "Engine": "V-6",
            "Trans": null,
            "Notes": null,
            "TowDesc": "Bumper Pull - Weight Carrying",
            "GearRatio": null,
            "TowCapacity": 7842
        }
    },
    {
        "Year": 2006,
        "Make": "Mercedes-Benz",
        "ModelTrim": "ML 500",
        "TowingCapacity": {
            "Id": 15977,
            "Year": 2006,
            "TypeDesc": "Sport Utility Vehicle",
            "MfgDesc": "Mercedes-Benz",
            "MakeTrim": "ML 500",
            "DriveTypeDesc": "Not Available",
            "Engine": "V-8",
            "Trans": null,
            "Notes": null,
            "TowDesc": "Bumper Pull - Weight Carrying",
            "GearRatio": null,
            "TowCapacity": 7842
        }
    },
    {
        "Year": 2006,
        "Make": "Mercedes-Benz",
        "ModelTrim": "R-Class",
        "TowingCapacity": {
            "Id": 15978,
            "Year": 2006,
            "TypeDesc": "Station Wagon",
            "MfgDesc": "Mercedes-Benz",
            "MakeTrim": "R-Class",
            "DriveTypeDesc": "Not Available",
            "Engine": "All",
            "Trans": null,
            "Notes": null,
            "TowDesc": "Bumper Pull - Weight Carrying",
            "GearRatio": null,
            "TowCapacity": 4705
        }
    }
]