[
  {
    "key": "kawasaki",
    "url": "https://bikez.com/motorcycles/kawasaki_j300_2014.php",
    "make": "Kawasaki",
    "model": "J300",
    "year": 2014,
    "type": "Scooter",
    "wet_weight": 421.1,
    "front_tire_width": 4.72,
    "rear_tire_width": 5.91,
    "wheelbase": 61.2
  },
  {
    "key": "kawasaki",
    "url": "https://bikez.com/motorcycles/kawasaki_er-6f_2014.php",
    "make": "Kawasaki",
    "model": "ER-6f",
    "year": 2014,
    "type": "Naked bike",
    "wet_weight": 460.8,
    "front_tire_width": 4.72,
    "rear_tire_width": 6.3,
    "wheelbase": 55.5
  },
  {
    "key": "kawasaki",
    "url": "https://bikez.com/motorcycles/kawasaki_estrella_special_edition_2014.php",
    "make": "Kawasaki",
    "model": "Estrella Special Edition",
    "year": 2014,
    "type": "Allround",
    "wet_weight": 354.9,
    "front_tire_width": 3.54,
    "rear_tire_width": 4.33,
    "wheelbase": null
  },
  {
    "key": "kawasaki",
    "url": "https://bikez.com/motorcycles/kawasaki_250tr_2014.php",
    "make": "Kawasaki",
    "model": "250TR",
    "year": 2014,
    "type": "Enduro / offroad",
    "wet_weight": 337.3,
    "front_tire_width": 3.54,
    "rear_tire_width": 4.33,
    "wheelbase": 65
  },
  {
    "key": "kawasaki",
    "url": "https://bikez.com/motorcycles/kawasaki_er-4n_2014.php",
    "make": "Kawasaki",
    "model": "ER-4n",
    "year": 2014,
    "type": "Naked bike",
    "wet_weight": 438.7,
    "front_tire_width": 4.72,
    "rear_tire_width": 6.3,
    "wheelbase": 55.5
  },
  {
    "key": "kawasaki",
    "url": "https://bikez.com/motorcycles/kawasaki_1400_gtr_2014.php",
    "make": "Kawasaki",
    "model": "1400 GTR",
    "year": 2014,
    "type": "Sport touring",
    "wet_weight": 687.8,
    "front_tire_width": 4.72,
    "rear_tire_width": 7.48,
    "wheelbase": 59.8
  },
  {
    "key": "kawasaki",
    "url": "https://bikez.com/motorcycles/kawasaki_estrella_2014.php",
    "make": "Kawasaki",
    "model": "Estrella",
    "year": 2014,
    "type": "Allround",
    "wet_weight": 330.8,
    "front_tire_width": 3.54,
    "rear_tire_width": 4.33,
    "wheelbase": null
  },
  {
    "key": "kawasaki",
    "url": "https://bikez.com/motorcycles/kawasaki_d-tracker_x_2014.php",
    "make": "Kawasaki",
    "model": "D-Tracker X",
    "year": 2014,
    "type": "Super motard",
    "wet_weight": 304.2,
    "front_tire_width": 3.94,
    "rear_tire_width": 4.72,
    "wheelbase": 56.5
  },
  {
    "key": "kawasaki",
    "url": "https://bikez.com/motorcycles/kawasaki_er-4n_abs_2014.php",
    "make": "Kawasaki",
    "model": "ER-4n ABS",
    "year": 2014,
    "type": "Naked bike",
    "wet_weight": 447.5,
    "front_tire_width": 4.72,
    "rear_tire_width": 6.3,
    "wheelbase": 55.5
  },
  {
    "key": "kawasaki",
    "url": "https://bikez.com/motorcycles/kawasaki_j300_special_edition_2014.php",
    "make": "Kawasaki",
    "model": "J300 Special Edition",
    "year": 2014,
    "type": "Scooter",
    "wet_weight": 421.1,
    "front_tire_width": 4.72,
    "rear_tire_width": 5.91,
    "wheelbase": 61.2
  },
  {
    "key": "kawasaki",
    "url": "https://bikez.com/motorcycles/kawasaki_1400gtr_grand_tourer_2014.php",
    "make": "Kawasaki",
    "model": "1400GTR Grand Tourer",
    "year": 2014,
    "type": "Sport touring",
    "wet_weight": 694.5,
    "front_tire_width": 4.72,
    "rear_tire_width": 7.48,
    "wheelbase": 59.8
  },
  {
    "key": "kawasaki",
    "url": "https://bikez.com/motorcycles/kawasaki_d-tracker_150_2014.php",
    "make": "Kawasaki",
    "model": "D-Tracker 150",
    "year": 2014,
    "type": "Super motard",
    "wet_weight": 279,
    "front_tire_width": 3.94,
    "rear_tire_width": 4.72,
    "wheelbase": 49.4
  },
  {
    "key": "kawasaki",
    "url": "https://bikez.com/motorcycles/kawasaki_klr_650_2014.php",
    "make": "Kawasaki",
    "model": "KLR 650",
    "year": 2014,
    "type": "Super motard",
    "wet_weight": 432,
    "front_tire_width": null,
    "rear_tire_width": 5.12,
    "wheelbase": 58.3
  },
  {
    "key": "kawasaki",
    "url": "https://bikez.com/motorcycles/kawasaki_klr_650_new_edition_2014.php",
    "make": "Kawasaki",
    "model": "KLR 650 New Edition",
    "year": 2014,
    "type": "Super motard",
    "wet_weight": 432,
    "front_tire_width": null,
    "rear_tire_width": 5.12,
    "wheelbase": 58.3
  },
  {
    "key": "kawasaki",
    "url": "https://bikez.com/motorcycles/kawasaki_er-6n_2014.php",
    "make": "Kawasaki",
    "model": "ER-6n",
    "year": 2014,
    "type": "Naked bike",
    "wet_weight": 449.7,
    "front_tire_width": 4.72,
    "rear_tire_width": 6.3,
    "wheelbase": 55.5
  },
  {
    "key": "kawasaki",
    "url": "https://bikez.com/motorcycles/kawasaki_klx_140_2014.php",
    "make": "Kawasaki",
    "model": "KLX 140",
    "year": 2014,
    "type": "Enduro / offroad",
    "wet_weight": 205,
    "front_tire_width": 2.76,
    "rear_tire_width": 3.54,
    "wheelbase": 49.6
  },
  {
    "key": "kawasaki",
    "url": "https://bikez.com/motorcycles/kawasaki_concours_14_abs_2014.php",
    "make": "Kawasaki",
    "model": "Concours  14 ABS",
    "year": 2014,
    "type": "Sport touring",
    "wet_weight": 688,
    "front_tire_width": 4.72,
    "rear_tire_width": 7.48,
    "wheelbase": 59.8
  },
  {
    "key": "kawasaki",
    "url": "https://bikez.com/motorcycles/kawasaki_klx_110_2014.php",
    "make": "Kawasaki",
    "model": "KLX 110",
    "year": 2014,
    "type": "Enduro / offroad",
    "wet_weight": 168,
    "front_tire_width": 2.5,
    "rear_tire_width": 3,
    "wheelbase": 42.3
  },
  {
    "key": "kawasaki",
    "url": "https://bikez.com/motorcycles/kawasaki_klx_110l_2014.php",
    "make": "Kawasaki",
    "model": "KLX 110L",
    "year": 2014,
    "type": "Enduro / offroad",
    "wet_weight": 168,
    "front_tire_width": 2.5,
    "rear_tire_width": 3,
    "wheelbase": 42.3
  },
  {
    "key": "kawasaki",
    "url": "https://bikez.com/motorcycles/kawasaki_klx_140l_2014.php",
    "make": "Kawasaki",
    "model": "KLX 140L",
    "year": 2014,
    "type": "Enduro / offroad",
    "wet_weight": 209.4,
    "front_tire_width": 2.76,
    "rear_tire_width": 3.54,
    "wheelbase": 50.6
  },
  {
    "key": "kawasaki",
    "url": "https://bikez.com/motorcycles/kawasaki_klx_250s_2014.php",
    "make": "Kawasaki",
    "model": "KLX 250S",
    "year": 2014,
    "type": "Super motard",
    "wet_weight": 297.7,
    "front_tire_width": null,
    "rear_tire_width": 3.94,
    "wheelbase": 56.3
  },
  {
    "key": "kawasaki",
    "url": "https://bikez.com/motorcycles/kawasaki_klx125_2014.php",
    "make": "Kawasaki",
    "model": "KLX125",
    "year": 2014,
    "type": "Super motard",
    "wet_weight": 249.1,
    "front_tire_width": 2.76,
    "rear_tire_width": 3.54,
    "wheelbase": 50.6
  },
  {
    "key": "kawasaki",
    "url": "https://bikez.com/motorcycles/kawasaki_klx250_2014.php",
    "make": "Kawasaki",
    "model": "KLX250",
    "year": 2014,
    "type": "Super motard",
    "wet_weight": 304.2,
    "front_tire_width": 3,
    "rear_tire_width": 4.6,
    "wheelbase": 56.3
  },
  {
    "key": "kawasaki",
    "url": "https://bikez.com/motorcycles/kawasaki_kx_450f_2014.php",
    "make": "Kawasaki",
    "model": "KX 450F",
    "year": 2014,
    "type": "Cross / motocross",
    "wet_weight": 248,
    "front_tire_width": 3.15,
    "rear_tire_width": 4.72,
    "wheelbase": 58.3
  },
  {
    "key": "kawasaki",
    "url": "https://bikez.com/motorcycles/kawasaki_ninja_1000_2014.php",
    "make": "Kawasaki",
    "model": "Ninja  1000",
    "year": 2014,
    "type": "Sport",
    "wet_weight": 509.4,
    "front_tire_width": 4.72,
    "rear_tire_width": 7.48,
    "wheelbase": 56.9
  },
  {
    "key": "kawasaki",
    "url": "https://bikez.com/motorcycles/kawasaki_ninja_250r_2014.php",
    "make": "Kawasaki",
    "model": "Ninja  250R",
    "year": 2014,
    "type": "Sport",
    "wet_weight": 374.9,
    "front_tire_width": 4.33,
    "rear_tire_width": 5.12,
    "wheelbase": 55.1
  },
  {
    "key": "kawasaki",
    "url": "https://bikez.com/motorcycles/kawasaki_ninja_zx-10r_abs_2014.php",
    "make": "Kawasaki",
    "model": "Ninja  ZX-10R ABS",
    "year": 2014,
    "type": "Sport",
    "wet_weight": 443.2,
    "front_tire_width": 4.72,
    "rear_tire_width": 7.48,
    "wheelbase": 56.1
  },
  {
    "key": "kawasaki",
    "url": "https://bikez.com/motorcycles/kawasaki_ninja_zx-6r_636_2014.php",
    "make": "Kawasaki",
    "model": "Ninja ZX-6R 636",
    "year": 2014,
    "type": "Sport",
    "wet_weight": 423.3,
    "front_tire_width": 4.72,
    "rear_tire_width": 7.09,
    "wheelbase": 54.9
  },
  {
    "key": "kawasaki",
    "url": "https://bikez.com/motorcycles/kawasaki_ninja_zx-6r_2014.php",
    "make": "Kawasaki",
    "model": "Ninja  ZX-6R",
    "year": 2014,
    "type": "Sport",
    "wet_weight": 423.4,
    "front_tire_width": 4.72,
    "rear_tire_width": 7.09,
    "wheelbase": 54.9
  },
  {
    "key": "kawasaki",
    "url": "https://bikez.com/motorcycles/kawasaki_ninja_zx-10r_2014.php",
    "make": "Kawasaki",
    "model": "Ninja  ZX-10R",
    "year": 2014,
    "type": "Sport",
    "wet_weight": 436.6,
    "front_tire_width": 4.72,
    "rear_tire_width": 7.48,
    "wheelbase": 56.1
  },
  {
    "key": "kawasaki",
    "url": "https://bikez.com/motorcycles/kawasaki_ninja_300_se_2014.php",
    "make": "Kawasaki",
    "model": "Ninja  300 SE",
    "year": 2014,
    "type": "Sport",
    "wet_weight": 387.7,
    "front_tire_width": 4.33,
    "rear_tire_width": 5.51,
    "wheelbase": 55.3
  },
  {
    "key": "kawasaki",
    "url": "https://bikez.com/motorcycles/kawasaki_kx85-ii_2014.php",
    "make": "Kawasaki",
    "model": "KX85-II",
    "year": 2014,
    "type": "Cross / motocross",
    "wet_weight": 169.8,
    "front_tire_width": 2.76,
    "rear_tire_width": 3.54,
    "wheelbase": 51.6
  },
  {
    "key": "kawasaki",
    "url": "https://bikez.com/motorcycles/kawasaki_ninja_250_2014.php",
    "make": "Kawasaki",
    "model": "Ninja 250",
    "year": 2014,
    "type": "Sport",
    "wet_weight": 374.9,
    "front_tire_width": 4.33,
    "rear_tire_width": 5.12,
    "wheelbase": 55.1
  },
  {
    "key": "kawasaki",
    "url": "https://bikez.com/motorcycles/kawasaki_kx_85_2014.php",
    "make": "Kawasaki",
    "model": "KX 85",
    "year": 2014,
    "type": "Cross / motocross",
    "wet_weight": 152.1,
    "front_tire_width": 2.76,
    "rear_tire_width": 3.54,
    "wheelbase": 49.4
  },
  {
    "key": "kawasaki",
    "url": "https://bikez.com/motorcycles/kawasaki_ninja_300_abs_2014.php",
    "make": "Kawasaki",
    "model": "Ninja  300 ABS",
    "year": 2014,
    "type": "Sport",
    "wet_weight": 383.7,
    "front_tire_width": 4.33,
    "rear_tire_width": 5.51,
    "wheelbase": 55.3
  },
  {
    "key": "kawasaki",
    "url": "https://bikez.com/motorcycles/kawasaki_kx85-i_2014.php",
    "make": "Kawasaki",
    "model": "KX85-I",
    "year": 2014,
    "type": "Minibike, cross",
    "wet_weight": 165.3,
    "front_tire_width": 2.76,
    "rear_tire_width": 3.54,
    "wheelbase": 49.4
  },
  {
    "key": "kawasaki",
    "url": "https://bikez.com/motorcycles/kawasaki_kx_100_2014.php",
    "make": "Kawasaki",
    "model": "KX 100",
    "year": 2014,
    "type": "Cross / motocross",
    "wet_weight": 156.5,
    "front_tire_width": 2.76,
    "rear_tire_width": 3.54,
    "wheelbase": 50.8
  },
  {
    "key": "kawasaki",
    "url": "https://bikez.com/motorcycles/kawasaki_ninja_zx-14r_2014.php",
    "make": "Kawasaki",
    "model": "Ninja  ZX-14R",
    "year": 2014,
    "type": "Sport",
    "wet_weight": 584.3,
    "front_tire_width": 4.72,
    "rear_tire_width": 7.48,
    "wheelbase": 58.3
  },
  {
    "key": "kawasaki",
    "url": "https://bikez.com/motorcycles/kawasaki_ninja_400r_special_edition_2014.php",
    "make": "Kawasaki",
    "model": "Ninja 400R Special Edition",
    "year": 2014,
    "type": "Sport",
    "wet_weight": 465.2,
    "front_tire_width": 4.72,
    "rear_tire_width": 6.3,
    "wheelbase": 55.5
  },
  {
    "key": "kawasaki",
    "url": "https://bikez.com/motorcycles/kawasaki_ninja_300_2014.php",
    "make": "Kawasaki",
    "model": "Ninja  300",
    "year": 2014,
    "type": "Sport",
    "wet_weight": 379.2,
    "front_tire_width": 4.33,
    "rear_tire_width": 5.51,
    "wheelbase": 55.3
  },
  {
    "key": "kawasaki",
    "url": "https://bikez.com/motorcycles/kawasaki_ninja_1000_abs_2014.php",
    "make": "Kawasaki",
    "model": "Ninja  1000 ABS",
    "year": 2014,
    "type": "Sport",
    "wet_weight": 509.4,
    "front_tire_width": 4.72,
    "rear_tire_width": 7.48,
    "wheelbase": 56.9
  },
  {
    "key": "kawasaki",
    "url": "https://bikez.com/motorcycles/kawasaki_ninja_650_2014.php",
    "make": "Kawasaki",
    "model": "Ninja  650",
    "year": 2014,
    "type": "Sport",
    "wet_weight": 460.8,
    "front_tire_width": 4.72,
    "rear_tire_width": 6.3,
    "wheelbase": 55.5
  },
  {
    "key": "kawasaki",
    "url": "https://bikez.com/motorcycles/kawasaki_ninja_300_2014.php",
    "make": "Kawasaki",
    "model": "Ninja 300",
    "year": 2014,
    "type": "Sport",
    "wet_weight": 379.2,
    "front_tire_width": 4.33,
    "rear_tire_width": 5.51,
    "wheelbase": 55.3
  },
  {
    "key": "kawasaki",
    "url": "https://bikez.com/motorcycles/kawasaki_ninja_300_abs_2014.php",
    "make": "Kawasaki",
    "model": "Ninja 300 ABS",
    "year": 2014,
    "type": "Sport",
    "wet_weight": 383.7,
    "front_tire_width": 4.33,
    "rear_tire_width": 5.51,
    "wheelbase": 55.3
  },
  {
    "key": "kawasaki",
    "url": "https://bikez.com/motorcycles/kawasaki_ninja_zx-6r_636_performance_2014.php",
    "make": "Kawasaki",
    "model": "Ninja ZX-6R 636 Performance",
    "year": 2014,
    "type": "Sport",
    "wet_weight": 421.1,
    "front_tire_width": 4.72,
    "rear_tire_width": 7.09,
    "wheelbase": 55.1
  },
  {
    "key": "kawasaki",
    "url": "https://bikez.com/motorcycles/kawasaki_ninja_zx-6r_abs_2014.php",
    "make": "Kawasaki",
    "model": "Ninja  ZX-6R ABS",
    "year": 2014,
    "type": "Sport",
    "wet_weight": 427.8,
    "front_tire_width": 4.72,
    "rear_tire_width": 7.09,
    "wheelbase": 54.9
  },
  {
    "key": "kawasaki",
    "url": "https://bikez.com/motorcycles/kawasaki_kx_65_2014.php",
    "make": "Kawasaki",
    "model": "KX 65",
    "year": 2014,
    "type": "Cross / motocross",
    "wet_weight": 132.2,
    "front_tire_width": 2.36,
    "rear_tire_width": 3.15,
    "wheelbase": 44.1
  },
  {
    "key": "kawasaki",
    "url": "https://bikez.com/motorcycles/kawasaki_ninja_zx-14r_abs_2014.php",
    "make": "Kawasaki",
    "model": "Ninja  ZX-14R ABS",
    "year": 2014,
    "type": "Sport",
    "wet_weight": 590.9,
    "front_tire_width": 4.72,
    "rear_tire_width": 7.48,
    "wheelbase": 58.3
  },
  {
    "key": "kawasaki",
    "url": "https://bikez.com/motorcycles/kawasaki_kx_250f_2014.php",
    "make": "Kawasaki",
    "model": "KX 250F",
    "year": 2014,
    "type": "Cross / motocross",
    "wet_weight": 233.6,
    "front_tire_width": 3.15,
    "rear_tire_width": 3.94,
    "wheelbase": 58.1
  },
  {
    "key": "kawasaki",
    "url": "https://bikez.com/motorcycles/kawasaki_ninja_300_abs_se_2014.php",
    "make": "Kawasaki",
    "model": "Ninja  300 ABS SE",
    "year": 2014,
    "type": "Sport",
    "wet_weight": 387.7,
    "front_tire_width": 4.33,
    "rear_tire_width": 5.51,
    "wheelbase": 55.3
  },
  {
    "key": "kawasaki",
    "url": "https://bikez.com/motorcycles/kawasaki_versys_2014.php",
    "make": "Kawasaki",
    "model": "Versys",
    "year": 2014,
    "type": "Allround",
    "wet_weight": 454.2,
    "front_tire_width": 4.72,
    "rear_tire_width": 6.3,
    "wheelbase": 55.7
  },
  {
    "key": "kawasaki",
    "url": "https://bikez.com/motorcycles/kawasaki_ninja_650_abs_2014.php",
    "make": "Kawasaki",
    "model": "Ninja  650 ABS",
    "year": 2014,
    "type": "Sport",
    "wet_weight": 465.3,
    "front_tire_width": 4.72,
    "rear_tire_width": 6.3,
    "wheelbase": 55.5
  },
  {
    "key": "kawasaki",
    "url": "https://bikez.com/motorcycles/kawasaki_ninja_400_2014.php",
    "make": "Kawasaki",
    "model": "Ninja 400",
    "year": 2014,
    "type": "Sport",
    "wet_weight": 460.8,
    "front_tire_width": 4.72,
    "rear_tire_width": 6.3,
    "wheelbase": 55.5
  },
  {
    "key": "kawasaki",
    "url": "https://bikez.com/motorcycles/kawasaki_ninja_zx-14r_abs_special_edition_2014.php",
    "make": "Kawasaki",
    "model": "Ninja ZX-14R ABS Special Edition",
    "year": 2014,
    "type": "Sport",
    "wet_weight": 590.8,
    "front_tire_width": 4.72,
    "rear_tire_width": 7.48,
    "wheelbase": 58.3
  },
  {
    "key": "kawasaki",
    "url": "https://bikez.com/motorcycles/kawasaki_versys_abs_2014.php",
    "make": "Kawasaki",
    "model": "Versys  ABS",
    "year": 2014,
    "type": "Allround",
    "wet_weight": 460.8,
    "front_tire_width": 4.72,
    "rear_tire_width": 6.3,
    "wheelbase": 55.7
  },
  {
    "key": "kawasaki",
    "url": "https://bikez.com/motorcycles/kawasaki_versys_1000_2014.php",
    "make": "Kawasaki",
    "model": "Versys 1000",
    "year": 2014,
    "type": "Allround",
    "wet_weight": 526.9,
    "front_tire_width": 4.72,
    "rear_tire_width": 7.09,
    "wheelbase": 59.8
  },
  {
    "key": "kawasaki",
    "url": "https://bikez.com/motorcycles/kawasaki_versys_tourer_2014.php",
    "make": "Kawasaki",
    "model": "Versys Tourer",
    "year": 2014,
    "type": "Allround",
    "wet_weight": 454.2,
    "front_tire_width": 4.72,
    "rear_tire_width": 6.3,
    "wheelbase": 55.7
  },
  {
    "key": "kawasaki",
    "url": "https://bikez.com/motorcycles/kawasaki_vn_1700_classic_2014.php",
    "make": "Kawasaki",
    "model": "VN 1700 Classic",
    "year": 2014,
    "type": "Custom / cruiser",
    "wet_weight": 769.4,
    "front_tire_width": 5.12,
    "rear_tire_width": 6.69,
    "wheelbase": 65.6
  },
  {
    "key": "kawasaki",
    "url": "https://bikez.com/motorcycles/kawasaki_vn_1700_classic_tourer_2014.php",
    "make": "Kawasaki",
    "model": "VN 1700 Classic Tourer",
    "year": 2014,
    "type": "Touring",
    "wet_weight": 842.2,
    "front_tire_width": 5.12,
    "rear_tire_width": 6.69,
    "wheelbase": 65.6
  },
  {
    "key": "kawasaki",
    "url": "https://bikez.com/motorcycles/kawasaki_vulcan_1700_nomad_2014.php",
    "make": "Kawasaki",
    "model": "Vulcan  1700 Nomad",
    "year": 2014,
    "type": "Touring",
    "wet_weight": 834,
    "front_tire_width": 5.12,
    "rear_tire_width": 6.69,
    "wheelbase": 65.6
  },
  {
    "key": "kawasaki",
    "url": "https://bikez.com/motorcycles/kawasaki_vn_900_classic_special_edition_2014.php",
    "make": "Kawasaki",
    "model": "VN 900 Classic Special Edition",
    "year": 2014,
    "type": "Custom / cruiser",
    "wet_weight": 621.7,
    "front_tire_width": 5.12,
    "rear_tire_width": 7.09,
    "wheelbase": 64.8
  },
  {
    "key": "kawasaki",
    "url": "https://bikez.com/motorcycles/kawasaki_w800_special_edition_2014.php",
    "make": "Kawasaki",
    "model": "W800 Special Edition",
    "year": 2014,
    "type": "Classic",
    "wet_weight": 478.4,
    "front_tire_width": 3.94,
    "rear_tire_width": 5.12,
    "wheelbase": 57.7
  },
  {
    "key": "kawasaki",
    "url": "https://bikez.com/motorcycles/kawasaki_vulcan_1700_voyager_2014.php",
    "make": "Kawasaki",
    "model": "Vulcan  1700 Voyager",
    "year": 2014,
    "type": "Touring",
    "wet_weight": 886,
    "front_tire_width": 5.12,
    "rear_tire_width": 6.69,
    "wheelbase": 65.6
  },
  {
    "key": "kawasaki",
    "url": "https://bikez.com/motorcycles/kawasaki_z1000_special_edition_2014.php",
    "make": "Kawasaki",
    "model": "Z1000 Special Edition",
    "year": 2014,
    "type": "Naked bike",
    "wet_weight": 485,
    "front_tire_width": 4.72,
    "rear_tire_width": 7.48,
    "wheelbase": 56.7
  },
  {
    "key": "kawasaki",
    "url": "https://bikez.com/motorcycles/kawasaki_w800_chrome_edition_2014.php",
    "make": "Kawasaki",
    "model": "W800 Chrome Edition",
    "year": 2014,
    "type": "Classic",
    "wet_weight": 480.6,
    "front_tire_width": 3.94,
    "rear_tire_width": 5.12,
    "wheelbase": 57.7
  },
  {
    "key": "kawasaki",
    "url": "https://bikez.com/motorcycles/kawasaki_vulcan_900_classic_lt_2014.php",
    "make": "Kawasaki",
    "model": "Vulcan  900 Classic LT",
    "year": 2014,
    "type": "Touring",
    "wet_weight": 657.1,
    "front_tire_width": 5.12,
    "rear_tire_width": 7.09,
    "wheelbase": 64.8
  },
  {
    "key": "kawasaki",
    "url": "https://bikez.com/motorcycles/kawasaki_vn_1700_voyager_2014.php",
    "make": "Kawasaki",
    "model": "VN 1700 Voyager",
    "year": 2014,
    "type": "Touring",
    "wet_weight": 895.1,
    "front_tire_width": 5.12,
    "rear_tire_width": 6.69,
    "wheelbase": 65.6
  },
  {
    "key": "kawasaki",
    "url": "https://bikez.com/motorcycles/kawasaki_vulcan_1700_classic_2014.php",
    "make": "Kawasaki",
    "model": "Vulcan  1700 Classic",
    "year": 2014,
    "type": "Custom / cruiser",
    "wet_weight": 761,
    "front_tire_width": 5.12,
    "rear_tire_width": 6.69,
    "wheelbase": 65.6
  },
  {
    "key": "kawasaki",
    "url": "https://bikez.com/motorcycles/kawasaki_vulcan_900_custom_2014.php",
    "make": "Kawasaki",
    "model": "Vulcan  900 Custom",
    "year": 2014,
    "type": "Custom / cruiser",
    "wet_weight": 610.8,
    "front_tire_width": null,
    "rear_tire_width": 7.09,
    "wheelbase": 64.8
  },
  {
    "key": "kawasaki",
    "url": "https://bikez.com/motorcycles/kawasaki_z250_2014.php",
    "make": "Kawasaki",
    "model": "Z250",
    "year": 2014,
    "type": "Naked bike",
    "wet_weight": 370.4,
    "front_tire_width": 4.33,
    "rear_tire_width": 5.51,
    "wheelbase": 55.1
  },
  {
    "key": "kawasaki",
    "url": "https://bikez.com/motorcycles/kawasaki_vulcan_1700_vaquero_2014.php",
    "make": "Kawasaki",
    "model": "Vulcan  1700 Vaquero",
    "year": 2014,
    "type": "Touring",
    "wet_weight": 835.7,
    "front_tire_width": 5.12,
    "rear_tire_width": 6.69,
    "wheelbase": 65.6
  },
  {
    "key": "kawasaki",
    "url": "https://bikez.com/motorcycles/kawasaki_vulcan_1700_vaquero_abs_se_2014.php",
    "make": "Kawasaki",
    "model": "Vulcan 1700 Vaquero ABS SE",
    "year": 2014,
    "type": "Touring",
    "wet_weight": 844.5,
    "front_tire_width": 5.12,
    "rear_tire_width": 6.69,
    "wheelbase": 65.6
  },
  {
    "key": "kawasaki",
    "url": "https://bikez.com/motorcycles/kawasaki_vulcan_1700_voyager_abs_2014.php",
    "make": "Kawasaki",
    "model": "Vulcan  1700 Voyager  ABS",
    "year": 2014,
    "type": "Touring",
    "wet_weight": 895.2,
    "front_tire_width": 5.12,
    "rear_tire_width": 6.69,
    "wheelbase": 65.5
  },
  {
    "key": "kawasaki",
    "url": "https://bikez.com/motorcycles/kawasaki_z1000_abs_2014.php",
    "make": "Kawasaki",
    "model": "Z1000 ABS",
    "year": 2014,
    "type": "Naked bike",
    "wet_weight": 487.3,
    "front_tire_width": 4.72,
    "rear_tire_width": 7.48,
    "wheelbase": 56.5
  },
  {
    "key": "kawasaki",
    "url": "https://bikez.com/motorcycles/kawasaki_z800_e_2014.php",
    "make": "Kawasaki",
    "model": "Z800 e",
    "year": 2014,
    "type": "Naked bike",
    "wet_weight": 498.2,
    "front_tire_width": 4.72,
    "rear_tire_width": 7.09,
    "wheelbase": 56.9
  },
  {
    "key": "kawasaki",
    "url": "https://bikez.com/motorcycles/kawasaki_vulcan_1700_vaquero_abs_2014.php",
    "make": "Kawasaki",
    "model": "Vulcan  1700 Vaquero  ABS",
    "year": 2014,
    "type": "Touring",
    "wet_weight": 844.5,
    "front_tire_width": 5.12,
    "rear_tire_width": 6.69,
    "wheelbase": 65.6
  },
  {
    "key": "kawasaki",
    "url": "https://bikez.com/motorcycles/kawasaki_vn_1700_voyager_custom_2014.php",
    "make": "Kawasaki",
    "model": "VN 1700 Voyager Custom",
    "year": 2014,
    "type": "Custom / cruiser",
    "wet_weight": 842.2,
    "front_tire_width": 5.12,
    "rear_tire_width": 6.69,
    "wheelbase": 65.6
  },
  {
    "key": "kawasaki",
    "url": "https://bikez.com/motorcycles/kawasaki_zrx1200_daeg_2014.php",
    "make": "Kawasaki",
    "model": "ZRX1200 DAEG",
    "year": 2014,
    "type": "Allround",
    "wet_weight": 607.4,
    "front_tire_width": 4.72,
    "rear_tire_width": 7.09,
    "wheelbase": 57.9
  },
  {
    "key": "kawasaki",
    "url": "https://bikez.com/motorcycles/kawasaki_zrx1200_daeg_black_limited_2014.php",
    "make": "Kawasaki",
    "model": "ZRX1200 DAEG Black Limited",
    "year": 2014,
    "type": "Allround",
    "wet_weight": 607.4,
    "front_tire_width": 4.72,
    "rear_tire_width": 7.09,
    "wheelbase": 57.9
  },
  {
    "key": "kawasaki",
    "url": "https://bikez.com/motorcycles/kawasaki_vulcan_900_classic_2014.php",
    "make": "Kawasaki",
    "model": "Vulcan  900 Classic",
    "year": 2014,
    "type": "Custom / cruiser",
    "wet_weight": 619.6,
    "front_tire_width": 5.12,
    "rear_tire_width": 7.09,
    "wheelbase": 64.8
  },
  {
    "key": "kawasaki",
    "url": "https://bikez.com/motorcycles/kawasaki_vulcan_1700_nomad_abs_2014.php",
    "make": "Kawasaki",
    "model": "Vulcan  1700 Nomad ABS",
    "year": 2014,
    "type": "Touring",
    "wet_weight": 842.3,
    "front_tire_width": 5.12,
    "rear_tire_width": 6.69,
    "wheelbase": 65.6
  },
  {
    "key": "kawasaki",
    "url": "https://bikez.com/motorcycles/kawasaki_vn_900_custom_2014.php",
    "make": "Kawasaki",
    "model": "VN 900 Custom",
    "year": 2014,
    "type": "Custom / cruiser",
    "wet_weight": 612.9,
    "front_tire_width": 3.15,
    "rear_tire_width": 7.09,
    "wheelbase": 64.8
  },
  {
    "key": "kawasaki",
    "url": "https://bikez.com/motorcycles/kawasaki_w800_2014.php",
    "make": "Kawasaki",
    "model": "W800",
    "year": 2014,
    "type": "Classic",
    "wet_weight": 478.4,
    "front_tire_width": 3.94,
    "rear_tire_width": 5.12,
    "wheelbase": 57.7
  },
  {
    "key": "kawasaki",
    "url": "https://bikez.com/motorcycles/kawasaki_z800_2014.php",
    "make": "Kawasaki",
    "model": "Z800",
    "year": 2014,
    "type": "Naked bike",
    "wet_weight": 504.9,
    "front_tire_width": 4.72,
    "rear_tire_width": 7.09,
    "wheelbase": 56.9
  },
  {
    "key": "kawasaki",
    "url": "https://bikez.com/motorcycles/kawasaki_vn_900_classic_2014.php",
    "make": "Kawasaki",
    "model": "VN 900 Classic",
    "year": 2014,
    "type": "Custom / cruiser",
    "wet_weight": 621.7,
    "front_tire_width": 5.12,
    "rear_tire_width": 7.09,
    "wheelbase": 65
  }
]