[
  {
    "key": "Victory",
    "url": "https://bikez.com/motorcycles/victory_gunner_2018.php",
    "make": "Victory",
    "year": 2018,
    "type": "Custom / cruiser",
    "wet_weight": 683.4,
    "front_tire_width": 5.12,
    "rear_tire_width": 5.51,
    "wheelbase": 64.8
  },
  {
    "key": "Victory",
    "url": "https://bikez.com/motorcycles/victory_magnum_2018.php",
    "make": "Victory",
    "year": 2018,
    "type": "Touring",
    "wet_weight": 809.1,
    "front_tire_width": 4.72,
    "rear_tire_width": 7.09,
    "wheelbase": 65.7
  },
  {
    "key": "Victory",
    "url": "https://bikez.com/motorcycles/victory_high-ball_2018.php",
    "make": "Victory",
    "year": 2018,
    "type": "Custom / cruiser",
    "wet_weight": 757.1,
    "front_tire_width": 5.12,
    "rear_tire_width": 5.51,
    "wheelbase": 64.8
  },
  {
    "key": "Victory",
    "url": "https://bikez.com/motorcycles/victory_hammer_s_2018.php",
    "make": "Victory",
    "year": 2018,
    "type": "Custom / cruiser",
    "wet_weight": 672.4,
    "front_tire_width": 5.12,
    "rear_tire_width": 9.84,
    "wheelbase": 65.7
  },
  {
    "key": "Victory",
    "url": "https://bikez.com/motorcycles/victory_cross_country_tour_2018.php",
    "make": "Victory",
    "year": 2018,
    "type": "Touring",
    "wet_weight": 877.4,
    "front_tire_width": 5.12,
    "rear_tire_width": 7.09,
    "wheelbase": 65.7
  },
  {
    "key": "Victory",
    "url": "https://bikez.com/motorcycles/victory_cross_country_2018.php",
    "make": "Victory",
    "year": 2018,
    "type": "Touring",
    "wet_weight": 767.2,
    "front_tire_width": 5.12,
    "rear_tire_width": 7.09,
    "wheelbase": 65.7
  },
  {
    "key": "Victory",
    "url": "https://bikez.com/motorcycles/victory_magnum_x-1_2018.php",
    "make": "Victory",
    "year": 2018,
    "type": "Touring",
    "wet_weight": 822.3,
    "front_tire_width": 4.72,
    "rear_tire_width": 7.09,
    "wheelbase": 65.7
  },
  {
    "key": "Victory",
    "url": "https://bikez.com/motorcycles/victory_octane_2018.php",
    "make": "Victory",
    "year": 2018,
    "type": "Custom / cruiser",
    "wet_weight": 614.9,
    "front_tire_width": 5.12,
    "rear_tire_width": 6.3,
    "wheelbase": 62.1
  },
  {
    "key": "Victory",
    "url": "https://bikez.com/motorcycles/victory_vegas_2018.php",
    "make": "Victory",
    "year": 2018,
    "type": "Custom / cruiser",
    "wet_weight": 681.2,
    "front_tire_width": 3.54,
    "rear_tire_width": 7.09,
    "wheelbase": 67.1
  },
  {
    "key": "Victory",
    "url": "https://bikez.com/motorcycles/victory_vegas_8-ball_2018.php",
    "make": "Victory",
    "year": 2018,
    "type": "Custom / cruiser",
    "wet_weight": 763.8,
    "front_tire_width": 3.54,
    "rear_tire_width": 7.09,
    "wheelbase": 67.1
  },
  {
    "key": "Victory",
    "url": "https://bikez.com/motorcycles/victory_vision_2018.php",
    "make": "Victory",
    "year": 2018,
    "type": "Touring",
    "wet_weight": 899.5,
    "front_tire_width": 5.12,
    "rear_tire_width": 7.09,
    "wheelbase": 65.7
  }
]