{
    "1500 Quad Cab": [
        {
            "Year": 2005,
            "TypeDesc": "Truck",
            "MfgDesc": "Dodge Ram",
            "MakeTrim": "1500 Quad Cab",
            "DriveTypeDesc": "2 Wheel Drive",
            "Engine": "3.7L V-6",
            "Trans": null,
            "Notes": null,
            "TowDesc": "Bumper Pull - Weight Carrying",
            "TowCapacity": 3550
        },
        {
            "Year": 2005,
            "TypeDesc": "Truck",
            "MfgDesc": "Dodge Ram",
            "MakeTrim": "1500 Quad Cab",
            "DriveTypeDesc": "2 Wheel Drive",
            "Engine": "4.7L V-8",
            "Trans": null,
            "Notes": null,
            "TowDesc": "Bumper Pull - Weight Carrying",
            "TowCapacity": 7400
        },
        {
            "Year": 2005,
            "TypeDesc": "Truck",
            "MfgDesc": "Dodge Ram",
            "MakeTrim": "1500 Quad Cab",
            "DriveTypeDesc": "4 Wheel Drive / All-Wheel Drive",
            "Engine": "4.7L V-8",
            "Trans": null,
            "Notes": null,
            "TowDesc": "Bumper Pull - Weight Carrying",
            "TowCapacity": 7150
        },
        {
            "Year": 2005,
            "TypeDesc": "Truck",
            "MfgDesc": "Dodge Ram",
            "MakeTrim": "1500 Quad Cab",
            "DriveTypeDesc": "2 Wheel Drive",
            "Engine": "5.7L V-8",
            "Trans": null,
            "Notes": null,
            "TowDesc": "Bumper Pull - Weight Carrying",
            "TowCapacity": 8900
        },
        {
            "Year": 2005,
            "TypeDesc": "Truck",
            "MfgDesc": "Dodge Ram",
            "MakeTrim": "1500 Quad Cab",
            "DriveTypeDesc": "4 Wheel Drive / All-Wheel Drive",
            "Engine": "5.7L V-8",
            "Trans": null,
            "Notes": null,
            "TowDesc": "Bumper Pull - Weight Carrying",
            "TowCapacity": 8600
        }
    ],
    "1500 Regular Cab": [
        {
            "Year": 2005,
            "TypeDesc": "Truck",
            "MfgDesc": "Dodge Ram",
            "MakeTrim": "1500 Regular Cab",
            "DriveTypeDesc": "2 Wheel Drive",
            "Engine": "3.7L V-6",
            "Trans": null,
            "Notes": null,
            "TowDesc": "Bumper Pull - Weight Carrying",
            "TowCapacity": 3800
        },
        {
            "Year": 2005,
            "TypeDesc": "Truck",
            "MfgDesc": "Dodge Ram",
            "MakeTrim": "1500 Regular Cab",
            "DriveTypeDesc": "2 Wheel Drive",
            "Engine": "4.7L V-8",
            "Trans": null,
            "Notes": null,
            "TowDesc": "Bumper Pull - Weight Carrying",
            "TowCapacity": 7750
        },
        {
            "Year": 2005,
            "TypeDesc": "Truck",
            "MfgDesc": "Dodge Ram",
            "MakeTrim": "1500 Regular Cab",
            "DriveTypeDesc": "4 Wheel Drive / All-Wheel Drive",
            "Engine": "4.7L V-8",
            "Trans": null,
            "Notes": null,
            "TowDesc": "Bumper Pull - Weight Carrying",
            "TowCapacity": 7400
        },
        {
            "Year": 2005,
            "TypeDesc": "Truck",
            "MfgDesc": "Dodge Ram",
            "MakeTrim": "1500 Regular Cab",
            "DriveTypeDesc": "2 Wheel Drive",
            "Engine": "5.7L V-8",
            "Trans": null,
            "Notes": null,
            "TowDesc": "Bumper Pull - Weight Carrying",
            "TowCapacity": 9250
        },
        {
            "Year": 2005,
            "TypeDesc": "Truck",
            "MfgDesc": "Dodge Ram",
            "MakeTrim": "1500 Regular Cab",
            "DriveTypeDesc": "4 Wheel Drive / All-Wheel Drive",
            "Engine": "5.7L V-8",
            "Trans": null,
            "Notes": null,
            "TowDesc": "Bumper Pull - Weight Carrying",
            "TowCapacity": 8850
        }
    ],
    "2500 Quad Cab": [
        {
            "Year": 2005,
            "TypeDesc": "Truck",
            "MfgDesc": "Dodge Ram",
            "MakeTrim": "2500 Quad Cab",
            "DriveTypeDesc": "2 Wheel Drive",
            "Engine": "5.7L V-8",
            "Trans": null,
            "Notes": null,
            "TowDesc": "Bumper Pull - Weight Carrying",
            "TowCapacity": 11200
        },
        {
            "Year": 2005,
            "TypeDesc": "Truck",
            "MfgDesc": "Dodge Ram",
            "MakeTrim": "2500 Quad Cab",
            "DriveTypeDesc": "4 Wheel Drive / All-Wheel Drive",
            "Engine": "5.7L V-8",
            "Trans": null,
            "Notes": null,
            "TowDesc": "Bumper Pull - Weight Carrying",
            "TowCapacity": 10800
        },
        {
            "Year": 2005,
            "TypeDesc": "Truck",
            "MfgDesc": "Dodge Ram",
            "MakeTrim": "2500 Quad Cab",
            "DriveTypeDesc": "2 Wheel Drive",
            "Engine": "5.9L I-6 Turbo Diesel",
            "Trans": null,
            "Notes": null,
            "TowDesc": "Bumper Pull - Weight Carrying",
            "TowCapacity": 13400
        },
        {
            "Year": 2005,
            "TypeDesc": "Truck",
            "MfgDesc": "Dodge Ram",
            "MakeTrim": "2500 Quad Cab",
            "DriveTypeDesc": "4 Wheel Drive / All-Wheel Drive",
            "Engine": "5.9L I-6 Turbo Diesel",
            "Trans": null,
            "Notes": null,
            "TowDesc": "Bumper Pull - Weight Carrying",
            "TowCapacity": 13100
        }
    ],
    "2500 Regular Cab": [
        {
            "Year": 2005,
            "TypeDesc": "Truck",
            "MfgDesc": "Dodge Ram",
            "MakeTrim": "2500 Regular Cab",
            "DriveTypeDesc": "2 Wheel Drive",
            "Engine": "5.7L V-8",
            "Trans": null,
            "Notes": null,
            "TowDesc": "Bumper Pull - Weight Carrying",
            "TowCapacity": 11450
        },
        {
            "Year": 2005,
            "TypeDesc": "Truck",
            "MfgDesc": "Dodge Ram",
            "MakeTrim": "2500 Regular Cab",
            "DriveTypeDesc": "4 Wheel Drive / All-Wheel Drive",
            "Engine": "5.7L V-8",
            "Trans": null,
            "Notes": null,
            "TowDesc": "Bumper Pull - Weight Carrying",
            "TowCapacity": 11000
        },
        {
            "Year": 2005,
            "TypeDesc": "Truck",
            "MfgDesc": "Dodge Ram",
            "MakeTrim": "2500 Regular Cab",
            "DriveTypeDesc": "2 Wheel Drive",
            "Engine": "5.9L I-6 Turbo Diesel",
            "Trans": null,
            "Notes": null,
            "TowDesc": "Bumper Pull - Weight Carrying",
            "TowCapacity": 13600
        },
        {
            "Year": 2005,
            "TypeDesc": "Truck",
            "MfgDesc": "Dodge Ram",
            "MakeTrim": "2500 Regular Cab",
            "DriveTypeDesc": "4 Wheel Drive / All-Wheel Drive",
            "Engine": "5.9L I-6 Turbo Diesel",
            "Trans": null,
            "Notes": null,
            "TowDesc": "Bumper Pull - Weight Carrying",
            "TowCapacity": 13200
        }
    ],
    "3500 Quad Cab Dual Rear Wheel": [
        {
            "Year": 2005,
            "TypeDesc": "Truck",
            "MfgDesc": "Dodge Ram",
            "MakeTrim": "3500 Quad Cab Dual Rear Wheel",
            "DriveTypeDesc": "2 Wheel Drive",
            "Engine": "5.7L V-8",
            "Trans": null,
            "Notes": null,
            "TowDesc": "Bumper Pull - Weight Carrying",
            "TowCapacity": 10550
        },
        {
            "Year": 2005,
            "TypeDesc": "Truck",
            "MfgDesc": "Dodge Ram",
            "MakeTrim": "3500 Quad Cab Dual Rear Wheel",
            "DriveTypeDesc": "4 Wheel Drive / All-Wheel Drive",
            "Engine": "5.7L V-8",
            "Trans": null,
            "Notes": null,
            "TowDesc": "Bumper Pull - Weight Carrying",
            "TowCapacity": 10100
        },
        {
            "Year": 2005,
            "TypeDesc": "Truck",
            "MfgDesc": "Dodge Ram",
            "MakeTrim": "3500 Quad Cab Dual Rear Wheel",
            "DriveTypeDesc": "2 Wheel Drive",
            "Engine": "5.9L I-6 Turbo Diesel",
            "Trans": null,
            "Notes": null,
            "TowDesc": "Bumper Pull - Weight Carrying",
            "TowCapacity": 15900
        },
        {
            "Year": 2005,
            "TypeDesc": "Truck",
            "MfgDesc": "Dodge Ram",
            "MakeTrim": "3500 Quad Cab Dual Rear Wheel",
            "DriveTypeDesc": "4 Wheel Drive / All-Wheel Drive",
            "Engine": "5.9L I-6 Turbo Diesel",
            "Trans": null,
            "Notes": null,
            "TowDesc": "Bumper Pull - Weight Carrying",
            "TowCapacity": 15500
        }
    ],
    "3500 Quad Cab SRV": [
        {
            "Year": 2005,
            "TypeDesc": "Truck",
            "MfgDesc": "Dodge Ram",
            "MakeTrim": "3500 Quad Cab SRV",
            "DriveTypeDesc": "2 Wheel Drive",
            "Engine": "5.9L I-6 Turbo Diesel",
            "Trans": null,
            "Notes": null,
            "TowDesc": "Bumper Pull - Weight Carrying",
            "TowCapacity": 16350
        },
        {
            "Year": 2005,
            "TypeDesc": "Truck",
            "MfgDesc": "Dodge Ram",
            "MakeTrim": "3500 Quad Cab SRV",
            "DriveTypeDesc": "4 Wheel Drive / All-Wheel Drive",
            "Engine": "5.9L I-6 Turbo Diesel",
            "Trans": null,
            "Notes": null,
            "TowDesc": "Bumper Pull - Weight Carrying",
            "TowCapacity": 15950
        }
    ],
    "3500 Regular Cab Dual Rear Wheel": [
        {
            "Year": 2005,
            "TypeDesc": "Truck",
            "MfgDesc": "Dodge Ram",
            "MakeTrim": "3500 Regular Cab Dual Rear Wheel",
            "DriveTypeDesc": "2 Wheel Drive",
            "Engine": "5.7L V-8",
            "Trans": null,
            "Notes": null,
            "TowDesc": "Bumper Pull - Weight Carrying",
            "TowCapacity": 10950
        },
        {
            "Year": 2005,
            "TypeDesc": "Truck",
            "MfgDesc": "Dodge Ram",
            "MakeTrim": "3500 Regular Cab Dual Rear Wheel",
            "DriveTypeDesc": "4 Wheel Drive / All-Wheel Drive",
            "Engine": "5.7L V-8",
            "Trans": null,
            "Notes": null,
            "TowDesc": "Bumper Pull - Weight Carrying",
            "TowCapacity": 10450
        },
        {
            "Year": 2005,
            "TypeDesc": "Truck",
            "MfgDesc": "Dodge Ram",
            "MakeTrim": "3500 Regular Cab Dual Rear Wheel",
            "DriveTypeDesc": "2 Wheel Drive",
            "Engine": "5.9L I-6 Turbo Diesel",
            "Trans": null,
            "Notes": null,
            "TowDesc": "Bumper Pull - Weight Carrying",
            "TowCapacity": 16250
        },
        {
            "Year": 2005,
            "TypeDesc": "Truck",
            "MfgDesc": "Dodge Ram",
            "MakeTrim": "3500 Regular Cab Dual Rear Wheel",
            "DriveTypeDesc": "4 Wheel Drive / All-Wheel Drive",
            "Engine": "5.9L I-6 Turbo Diesel",
            "Trans": null,
            "Notes": null,
            "TowDesc": "Bumper Pull - Weight Carrying",
            "TowCapacity": 15850
        }
    ]
}